.DS_Store
zbpy/__init__.py
zbpy/auth.py
zbpy/basicqueries.py
zbpy/client.py
zbpy/cryptography.py
zbpy/datasci.py
zbpy/indexedfieldentity.py
zbpy/pagination.py
zbpy/permissionentity.py
zbpy/queries.py
zbpy/test_zbpy.py
zbpy/util.py
zbpy/winsign.py
zbpy/zbprotocol_pb2.py
zbpy/zbprotocol_pb2_grpc.py
zbpy-0.1.1.dist-info/LICENSE
zbpy-0.1.1.dist-info/LICENSE.txt
zbpy-0.1.1.dist-info/METADATA
zbpy-0.1.1.dist-info/WHEEL
zbpy-0.1.1.dist-info/top_level.txt
zbpy-0.1.1.dist-info/RECORD
