Metadata-Version: 2.1
Name: zbpy
Version: 0.1.1
Summary: A Python SDK for interacting with Zetabase.
Home-page: https://github.com/zetabase/zbpy
Author: Austin Hochman
Author-email: awh76@cornell.edu
License: UNKNOWN
Platform: UNKNOWN
Classifier: Programming Language :: Python :: 3
Classifier: Programming Language :: Python :: 3.6
Classifier: Programming Language :: Python :: 3.7
Classifier: Programming Language :: Python :: 3.8
Classifier: License :: OSI Approved :: BSD License
Classifier: Operating System :: OS Independent
Classifier: Framework :: Jupyter
Classifier: Intended Audience :: Developers
Classifier: Natural Language :: English
Classifier: Topic :: Database
Classifier: Topic :: Scientific/Engineering :: Artificial Intelligence
Requires-Python: >=3.6
Requires-Dist: pandas (>=1.0.5)
Requires-Dist: numpy (>=1.19.0)
Requires-Dist: grpcio (>=1.29.0)
Requires-Dist: grpcio-tools (>=1.29.0)
Requires-Dist: phonenumbers (>=8.12.5)
Requires-Dist: ipython (>=6.4.0)
Requires-Dist: ipython-genutils (>=0.2.0)
Requires-Dist: protobuf (>=3.12.2)
Requires-Dist: packaging (>=17.1)
Requires-Dist: fastecdsa (>=2.1.2) ; platform_system == "Darwin"
Requires-Dist: fastecdsa (>=2.1.2) ; platform_system == "Linux"
Requires-Dist: starkbank-ecdsa (>=1.0.0) ; platform_system == "Windows"
